milieux/__init__.py
milieux/config.py
milieux/distro.py
milieux/env.py
milieux/errors.py
milieux/package.py
milieux/py.typed
milieux/utils.py
milieux/.config/example_config.toml
milieux/.vscode/settings.json
milieux/cli/__init__.py
milieux/cli/config.py
milieux/cli/distro.py
milieux/cli/doc.py
milieux/cli/env.py
milieux/cli/main.py
milieux/cli/scaffold.py
milieux/doc/__init__.py
milieux/doc/doc_template.yml.jinja
milieux/doc/extra.css.jinja
milieux/doc/home_template.md.jinja
milieux/doc/hooks/clean_search_html.py
milieux-0.2.7.dist-info/METADATA
milieux-0.2.7.dist-info/WHEEL
milieux-0.2.7.dist-info/entry_points.txt
milieux-0.2.7.dist-info/licenses/LICENSE
milieux-0.2.7.dist-info/RECORD
