Metadata-Version: 2.4
Name: milieux
Version: 0.2.7
Summary: Tool to assist in developing, building, and installing Python packages.
Project-URL: Documentation, https://github.com/jeremander/milieux#readme
Project-URL: Issues, https://github.com/jeremander/milieux/issues
Project-URL: Source, https://github.com/jeremander/milieux
Author-email: Jeremy Silver <jeremys@nessiness.com>
License-Expression: MIT
License-File: LICENSE
Keywords: virtualenv
Classifier: Programming Language :: Python
Requires-Python: >=3.10
Requires-Dist: fancy-dataclass>=0.7.3
Requires-Dist: griffe-typingdoc
Requires-Dist: hatch
Requires-Dist: jinja2
Requires-Dist: mkdocs-api-autonav
Requires-Dist: mkdocs-material
Requires-Dist: mkdocs>=1.6
Requires-Dist: mkdocstrings[python]
Requires-Dist: packaging
Requires-Dist: rich
Requires-Dist: ruff
Requires-Dist: tomli
Requires-Dist: typing-extensions>=4.10
Requires-Dist: uv>=0.5.16
